persian_print/__init__.py
persian_print/core.py
persian_print-0.1.4.dist-info/METADATA
persian_print-0.1.4.dist-info/WHEEL
persian_print-0.1.4.dist-info/top_level.txt
persian_print-0.1.4.dist-info/RECORD
