Metadata-Version: 2.4
Name: persian_print
Version: 0.1.4
Summary: A Python library for easy Persian printing with advanced features and automatic dependency installation.
Author-email: Manus Agent <agent@manus.im>
License: MIT
Project-URL: Homepage, https://github.com/manus-agent/persian_print
Project-URL: Bug Tracker, https://github.com/manus-agent/persian_print/issues
Classifier: Programming Language :: Python :: 3
Classifier: License :: OSI Approved :: MIT License
Classifier: Operating System :: OS Independent
Classifier: Topic :: Software Development :: Libraries :: Python Modules
Classifier: Topic :: Text Processing
Classifier: Natural Language :: Persian
Requires-Python: >=3.7
Requires-Dist: arabic-reshaper
Requires-Dist: python-bidi
